corpus_statistics/__init__.py
corpus_statistics/component_advanced.py
corpus_statistics/component_simple.py
corpus_statistics/corpustypes.py
corpus_statistics/dispersion_functions.py
corpus_statistics-0.1.1.dist-info/entry_points.txt
corpus_statistics-0.1.1.dist-info/LICENSE
corpus_statistics-0.1.1.dist-info/WHEEL
corpus_statistics-0.1.1.dist-info/METADATA
corpus_statistics-0.1.1.dist-info/RECORD
