Metadata-Version: 2.1
Name: corpus-statistics
Version: 0.1.1
Summary: A spaCy pipeline component for counting tokens a pipeline has seen.
License: MIT
Author: Peter Baumgartner
Author-email: 5107405+pmbaumgartner@users.noreply.github.com
Requires-Python: >=3.8,<3.11
Classifier: License :: OSI Approved :: MIT License
Classifier: Programming Language :: Python :: 3
Classifier: Programming Language :: Python :: 3.10
Classifier: Programming Language :: Python :: 3.8
Classifier: Programming Language :: Python :: 3.9
Requires-Dist: numpy (>=1.22.2,<2.0.0)
Requires-Dist: scipy (>=1.8.0,<2.0.0)
Requires-Dist: spacy (>=3.2.2,<4.0.0)
Requires-Dist: tqdm (>=4.62.3,<5.0.0)
